[
null,
{"id":1,"animationId":41,"consumable":true,"damage":{"critical":false,"elementId":0,"formula":"0","type":0,"variance":20},"description":"","effects":[{"code":11,"dataId":0,"value1":0,"value2":500}],"hitType":0,"iconIndex":176,"itypeId":1,"name":"Poção de Vida","note":"","occasion":0,"price":50,"repeats":1,"scope":7,"speed":0,"successRate":100,"tpGain":0},
{"id":2,"animationId":41,"consumable":true,"damage":{"critical":false,"elementId":0,"formula":"0","type":0,"variance":20},"description":"","effects":[{"code":12,"dataId":0,"value1":0,"value2":200}],"hitType":0,"iconIndex":176,"itypeId":1,"name":"Poção de Mana","note":"","occasion":0,"price":100,"repeats":1,"scope":7,"speed":0,"successRate":100,"tpGain":0},
{"id":3,"animationId":45,"consumable":true,"damage":{"critical":false,"elementId":0,"formula":"0","type":0,"variance":20},"description":"","effects":[{"code":22,"dataId":4,"value1":1,"value2":0},{"code":22,"dataId":5,"value1":1,"value2":0},{"code":22,"dataId":6,"value1":1,"value2":0},{"code":22,"dataId":7,"value1":1,"value2":0},{"code":22,"dataId":8,"value1":1,"value2":0},{"code":22,"dataId":9,"value1":1,"value2":0},{"code":22,"dataId":10,"value1":1,"value2":0}],"hitType":0,"iconIndex":176,"itypeId":1,"name":"Antídoto","note":"","occasion":0,"price":200,"repeats":1,"scope":7,"speed":0,"successRate":100,"tpGain":0},
{"id":4,"animationId":0,"consumable":true,"damage":{"critical":false,"elementId":0,"formula":"0","type":0,"variance":20},"description":"","effects":[{"code":31,"dataId":2,"value1":5,"value2":0},{"code":31,"dataId":3,"value1":5,"value2":0}],"hitType":0,"iconIndex":0,"itypeId":1,"name":"Estimulante","note":"","occasion":0,"price":100,"repeats":1,"scope":7,"speed":0,"successRate":100,"tpGain":0},
{"id":5,"animationId":0,"consumable":false,"damage":{"critical":false,"elementId":0,"formula":"0","type":0,"variance":20},"description":"Um amuleto antigo que foi dado à rainha naga para que\nela o protegesse de mãos erradas","effects":[],"hitType":0,"iconIndex":147,"itypeId":2,"name":"Amuleto da Rainha Naga","note":"","occasion":0,"price":0,"repeats":1,"scope":7,"speed":0,"successRate":100,"tpGain":0},
{"id":6,"animationId":0,"consumable":false,"damage":{"critical":false,"elementId":0,"formula":"0","type":0,"variance":20},"description":"Um bracelete usado e protegido pelo lobo alfa da\nalcateia da floresta.","effects":[],"hitType":0,"iconIndex":144,"itypeId":2,"name":"Bracelete do Lobo Alfa","note":"","occasion":0,"price":0,"repeats":1,"scope":7,"speed":0,"successRate":100,"tpGain":0},
{"id":7,"animationId":0,"consumable":false,"damage":{"critical":false,"elementId":0,"formula":"0","type":0,"variance":20},"description":"Um anel de grande poder atualmente situado nas mãos da\nRainha Acromântula.","effects":[],"hitType":0,"iconIndex":145,"itypeId":2,"name":"Anel da Rainha Acromântula","note":"","occasion":0,"price":0,"repeats":1,"scope":7,"speed":0,"successRate":100,"tpGain":0},
{"id":8,"animationId":0,"consumable":false,"damage":{"critical":false,"elementId":0,"formula":"0","type":0,"variance":20},"description":"Um cinturão que garante poder àquele que o vestir.\nAtualmente pertence ao Minotauro do Deserto.","effects":[],"hitType":0,"iconIndex":134,"itypeId":2,"name":"Cinturão do Minotauro","note":"","occasion":0,"price":0,"repeats":1,"scope":7,"speed":0,"successRate":100,"tpGain":0},
{"id":9,"animationId":0,"consumable":true,"damage":{"critical":false,"elementId":0,"formula":"0","type":0,"variance":20},"description":"Uma flor encontrada próxima da floresta dos lobisomens.\nKate pode precisar dela.","effects":[],"hitType":0,"iconIndex":181,"itypeId":1,"name":"Beladonna","note":"","occasion":0,"price":0,"repeats":1,"scope":0,"speed":0,"successRate":100,"tpGain":0},
{"id":10,"animationId":0,"consumable":false,"damage":{"critical":false,"elementId":0,"formula":"0","type":0,"variance":20},"description":"Uma carta enviada por alguem inesperado.","effects":[],"hitType":0,"iconIndex":192,"itypeId":2,"name":"Carta misteriosa","note":"","occasion":0,"price":0,"repeats":1,"scope":0,"speed":0,"successRate":100,"tpGain":0},
{"id":11,"animationId":0,"consumable":false,"damage":{"critical":false,"elementId":0,"formula":"0","type":0,"variance":20},"description":"Uma chave que abre a cela onde Saul se encontra.","effects":[],"hitType":0,"iconIndex":195,"itypeId":2,"name":"Chave do Porão de Medeia","note":"","occasion":0,"price":0,"repeats":1,"scope":7,"speed":0,"successRate":100,"tpGain":0},
{"id":12,"animationId":0,"consumable":false,"damage":{"critical":false,"elementId":0,"formula":"0","type":0,"variance":20},"description":"Um tesouro que estava sendo procurado pelo pai de Astrid.\nParabéns por encontrá-lo.","effects":[],"hitType":0,"iconIndex":210,"itypeId":2,"name":"Tesouro da Câmara do Deserto","note":"","occasion":0,"price":0,"repeats":1,"scope":7,"speed":0,"successRate":100,"tpGain":0}
]